{
  "userId": "1",
  "createdAt": "2025-10-21T22:43:40.567Z",
  "updatedAt": "2025-10-28T10:00:37.676Z",
  "personalData": {
    "fullName": "Бы Не",
    "firstName": "Бы",
    "lastName": "",
    "middleName": "Егоров",
    "birthDate": "04.08.1959",
    "birthPlace": "",
    "phone": "+70281032000",
    "email": "i@sergutin-1.ru",
    "address": "Краснодарский край, г Краснодар\n\nИНН",
    "passportSeries": "",
    "passportNumber": "",
    "inn": "575109340669",
    "snils": "",
    "maritalStatus": "",
    "occupation": "бы не",
    "workplace": ""
  },
  "caseNotes": [
    {
      "timestamp": "2025-10-21T22:43:40.566Z",
      "content": "у меня есть история дела, изучи и скажи что мне делать дальше : \"судебный пристав-исполнитель Полтавчук А. Запрашиваемые данные:\nинформацию о наличии автомототранспорта (модель, госномер, под выпуска, цвет кузова, дата. 2021\n•Транспортные средства:\nЛегковые автомобили седан; Не указано; БМВ 730 D; 1999г. 000;\nПервичный ПТС (уникальный номер регистрации) 60ТА990056; Наименование технологической\nоперации Первичная регистрация ТС; Наименование регистрационного документа Свидетельство о\nрегистрации транспортного средства (приказ МВД России Nº 346-93); Серия и номер регистрационного\nдокумента 77MМ832193; Дата выдачи регистрационного документа 30. 2021\n• Транспортные средства:\nЛегковые автомобили прочие; Не указано; ВАЗ 21063; 1992г. 000; Наименование технологической операции\nПервичная регистрация ТС; Наименование регистрационного документа Технический паспорт; Дата\nвыдачи регистрационного документа 10. 2021\n•Транспортные средства:\nЛегковые автомобили прочие; Не указано; МАЗДА 929; 1987г. 000; Наименование технологической операции\nВыдача дубликата регистрационного документа; Наименование регистрационного документа\nТехнический паспорт; Серия и номер регистрационного документа ГЖ383874; Дата выдачи\nрегистрационного документа 12",
      "importance": 9
    },
    {
      "timestamp": "2025-10-21T22:56:03.014Z",
      "content": "изучи ситуацию : \"судебный пристав-исполнитель Полтавчук А. Запрашиваемые данные:\nинформацию о наличии автомототранспорта (модель, госномер, под выпуска, цвет кузова, дата. 2021\n•Транспортные средства:\nЛегковые автомобили седан; Не указано; БМВ 730 D; 1999г. 000;\nПервичный ПТС (уникальный номер регистрации) 60ТА990056; Наименование технологической\nоперации Первичная регистрация ТС; Наименование регистрационного документа Свидетельство о\nрегистрации транспортного средства (приказ МВД России Nº 346-93); Серия и номер регистрационного\nдокумента 77MМ832193; Дата выдачи регистрационного документа 30. 2021\n• Транспортные средства:\nЛегковые автомобили прочие; Не указано; ВАЗ 21063; 1992г. 000; Наименование технологической операции\nПервичная регистрация ТС; Наименование регистрационного документа Технический паспорт; Дата\nвыдачи регистрационного документа 10. 2021\n•Транспортные средства:\nЛегковые автомобили прочие; Не указано; МАЗДА 929; 1987г. 000; Наименование технологической операции\nВыдача дубликата регистрационного документа; Наименование регистрационного документа\nТехнический паспорт; Серия и номер регистрационного документа ГЖ383874; Дата выдачи\nрегистрационного документа 12",
      "importance": 7
    },
    {
      "timestamp": "2025-10-21T22:59:52.986Z",
      "content": "2019 Nº733 \"Об обшероссийских классификаторах технико-\nэкономической и социальной информации\"\nсудебный пристав-исполинтель Полтавчук А. Запрашиваемые данные:\nинформацию о наличии автомототранспорта (молсль, госномер, под выпуска, ивст кузова. 2021\n• Транспортные средства:\nЛегковые автомобили седан; Не указано; БМВ 730 D; 1999г. документ: Свидетельство о регистрации транспортного средства (приказ МВД России Nº 346-93); Серия\nи номер: 77MM832193; Дата выдачи: 30. 2021\n• Транспортные средства:\nЛегковые автомобили прочис; Не указано; ВАЗ 21063; 1992г. документ: Технический паспорт; Дата\nвыдачи: 10. 2021\n• Транспортные средства:\nЛегковые автомобили прочие; Не указано; МАЗДА 929; 1987г. документ: Технический паспорт; Серия\nи номер: ГЖ383874; Дата выдачи: 12. 13:00 до 18:00\nот (полностью)_\nЕгорова\nЮрия Павловича\nСНИЛС:\nЦарицынский отдел судебчых приставо»\nBX. к 977 4937579\nгаспорт 45 07 Nº 08 2244\nзыдан ОРД. 20042\ne-mail ann 374 @yandex ru\nЗАЯВЛЕНИЕ\nПрошу приостаховить выполнение\nсудебного приказа в отконенни\nменя до окончання проверки\nмосго дела Нагатинской\nпрокурат урай. 124 Уголовно-\nпроцессуального кодекса Российской федерации, может быть обжаловано\nв Басманную межрайонную прокуратуру города Москвы или в суд. 2025\n23-33/049419@\nHa Nº\nО транспортном налоге (13734/3Г)\nЕгорову Ю. 2025 Nº330ж-2025/20450045/0н981-25, и сообщает, что по вопросу исчисления\nтранспортного налога на адрес Вашего места жительства, указанный в Вашем\nобращении, заказным письмом направлен ответ Управления от 20. Одновременно Управление сообщает, что согласно письму ГУ МВД России от\nNº45/17-288, транспортное средство, указанное в Вашем обращении, зарегистрировано\nна Ваше имя. Учитывая вышеизложенное, транспортный налог за указанное транспортное\nсредство по 2023 год включительно исчислен Вам ИФНС России Nº 24 по г. По вопросу снятия с регистрационного учета указанного транспортного средства\nВы вправе обратиться в органы ГИБДД. 2023 предусмотрена\nвозможность получения налоговых уведомлений для уплаты имущественных налогов\nв электронной форме через личный кабинет на едином портале государственных и\nмуниципальных услуг (ЕПГУ). 2007 Nº\n229-ФЗ «Об исполнительном производстве», постановления судебного пристава-\nисполнителя и других должностных лиц службы судебных приставов, их действия\n(бездействие) по исполнению исполнительного документа могут быть обжалованы\nсторонами исполнительного производства, иными лицами, чьи права и интересы\nнарушены такими действиями, в порядке подчиненности и оспорены в суде. 2007 Nº 229-Ф3 «Об\nисполнительном производстве», жалоба на постановление судебного пристава-\nисполнителя или заместителя старшего судебного пристава, за исключением\nпостановления, утвержденного старшим судебным приставом, на их действия\n(бездействие) подается старшему судебному приставу, в подчинении которого\nнаходится судебный пристав-исполнитель или заместитель старшего судебного\nпристава. Жалоба на постановление должностного лица службы судебных\nприставов, его действия (бездействие) может быть подана как непосредственно\nвышестоящему должностному лицу службы судебных приставов, так и через\nдолжностное лицо службы судебных приставов, постановление, действия\n(бездействие) которого обжалуются. 2007 Nº\n229-Ф3 «Об исполнительном производстве», постановления судебного пристава-\nисполнителя и других должностных лиц службы судебных приставов, их действия\n(бездействие) по исполнению исполнительного документа могут быть обжалованы\nсторонами исполнительного производства, иными лицами, чьи права и интересы\nнарушены такими действиями, в порядке подчиненности и оспорены в суде. 2007 Nº 229-Ф3 «Об\nисполнительном производстве», жалоба на постановление судебного пристава-\nисполнителя или заместителя старшего судебного пристава, за исключением\nпостановления, утвержденного старшим судебным приставом, на их действия\n(бездействие) подается старшему судебному приставу, в подчинении которого\nнаходится судебный пристав-исполнитель или заместитель старшего судебного\nпристава. Жалоба на постановление должностного лица службы судебных\nприставов, его действия (бездействие) может быть подана как непосредственно\nвышестоящему должностному лицу службы судебных приставов, так и через\nдолжностное лицо службы судебных приставов, постановление, действия\n(бездействие) которого обжалуются. Разъясняем, что в соответствии с частью 4 статьи 5 Федерального закона\nNº 59-Ф3 от 02 мая 2006 года «О порядке рассмотрения обращений граждан РФ»,\nвы имеете право обращаться с жалобой на принятое по обращению решение в\nадминистративном или судебном порядке в соответствии с законодательством\nРФ. 2025\nNº\n1952*-2025/20450029/Он2713-25\nНа Nº\nБасманной межрайонной прокуратурой рассмотрено Ваше обращение\nпо вопросу нарушения процедуры постановки на учет транспортного средства,\nвх. Дополнительно сообщаем Вам необходимо обратиться в органы ДПС\nс целью снятия автомашины с учета которой Вы не пользуетесь с целью не\nплатить налог за автотранспорт которым пользуется другой гражданин. Так же сообщаем, что Ваше право обжаловать данное решение\nпрокурору или в суд в порядке, установленном статьей 124 или статьей 125\nуголовно процессуального кодекса Российской Федерации. Материал списать в номенклатурное делопроизводство. 2019 Nº733 \"Об общероссийских классификаторах технико-\nэкономической и социальной информации\"\nсудебный пристав-исполнитель Полтавчук А. Запрашиваемые данные:\nинформацию о наличии автомототранспорта (модель, госномер, под выпуска, цвет кузова, дата. 2021\n•Транспортные средства:\nЛегковые автомобили седан; Не указано; БМВ 730 D; 1999г. 000;\nПервичный ПТС (уникальный номер регистрации) 60ТА990056; Наименование технологической\nоперации Первичная регистрация ТС; Наименование регистрационного документа Свидетельство о\nрегистрации транспортного средства (приказ МВД России Nº 346-93); Серия и номер регистрационного\nдокумента 77MМ832193; Дата выдачи регистрационного документа 30. 2021\n• Транспортные средства:\nЛегковые автомобили прочие; Не указано; ВАЗ 21063; 1992г. 000; Наименование технологической операции\nПервичная регистрация ТС; Наименование регистрационного документа Технический паспорт; Дата\nвыдачи регистрационного документа 10. 2021\n•Транспортные средства:\nЛегковые автомобили прочие; Не указано; МАЗДА 929; 1987г. 000; Наименование технологической операции\nВыдача дубликата регистрационного документа; Наименование регистрационного документа\nТехнический паспорт; Серия и номер регистрационного документа ГЖ383874; Дата выдачи\nрегистрационного документа 12",
      "importance": 10
    },
    {
      "timestamp": "2025-10-21T23:06:45.184Z",
      "content": "напиши Жалоба в суд: Если прокуратура откажет, подавайте жалобу в суд на действия (бездействие) прокуратуры",
      "importance": 3
    },
    {
      "timestamp": "2025-10-22T00:38:45.462Z",
      "content": "2019 Nº733 \"Об обшероссийских классификаторах технико-\nэкономической и социальной информации\"\nсудебный пристав-исполинтель Полтавчук А. Запрашиваемые данные:\nинформацию о наличии автомототранспорта (молсль, госномер, под выпуска, ивст кузова. 2021\n• Транспортные средства:\nЛегковые автомобили седан; Не указано; БМВ 730 D; 1999г. документ: Свидетельство о регистрации транспортного средства (приказ МВД России Nº 346-93); Серия\nи номер: 77MM832193; Дата выдачи: 30. 2021\n• Транспортные средства:\nЛегковые автомобили прочис; Не указано; ВАЗ 21063; 1992г. документ: Технический паспорт; Дата\nвыдачи: 10. 2021\n• Транспортные средства:\nЛегковые автомобили прочие; Не указано; МАЗДА 929; 1987г. документ: Технический паспорт; Серия\nи номер: ГЖ383874; Дата выдачи: 12. 13:00 до 18:00\nот (полностью)_\nЕгорова\nЮрия Павловича\nСНИЛС:\nЦарицынский отдел судебчых приставо»\nBX. к 977 4937579\nгаспорт 45 07 Nº 08 2244\nзыдан ОРД. 20042\ne-mail ann 374 @yandex ru\nЗАЯВЛЕНИЕ\nПрошу приостаховить выполнение\nсудебного приказа в отконенни\nменя до окончання проверки\nмосго дела Нагатинской\nпрокурат урай. 124 Уголовно-\nпроцессуального кодекса Российской федерации, может быть обжаловано\nв Басманную межрайонную прокуратуру города Москвы или в суд. 2025\n23-33/049419@\nHa Nº\nО транспортном налоге (13734/3Г)\nЕгорову Ю. 2025 Nº330ж-2025/20450045/0н981-25, и сообщает, что по вопросу исчисления\nтранспортного налога на адрес Вашего места жительства, указанный в Вашем\nобращении, заказным письмом направлен ответ Управления от 20. Одновременно Управление сообщает, что согласно письму ГУ МВД России от\nNº45/17-288, транспортное средство, указанное в Вашем обращении, зарегистрировано\nна Ваше имя. Учитывая вышеизложенное, транспортный налог за указанное транспортное\nсредство по 2023 год включительно исчислен Вам ИФНС России Nº 24 по г. По вопросу снятия с регистрационного учета указанного транспортного средства\nВы вправе обратиться в органы ГИБДД. 2023 предусмотрена\nвозможность получения налоговых уведомлений для уплаты имущественных налогов\nв электронной форме через личный кабинет на едином портале государственных и\nмуниципальных услуг (ЕПГУ). 2007 Nº\n229-ФЗ «Об исполнительном производстве», постановления судебного пристава-\nисполнителя и других должностных лиц службы судебных приставов, их действия\n(бездействие) по исполнению исполнительного документа могут быть обжалованы\nсторонами исполнительного производства, иными лицами, чьи права и интересы\nнарушены такими действиями, в порядке подчиненности и оспорены в суде. 2007 Nº 229-Ф3 «Об\nисполнительном производстве», жалоба на постановление судебного пристава-\nисполнителя или заместителя старшего судебного пристава, за исключением\nпостановления, утвержденного старшим судебным приставом, на их действия\n(бездействие) подается старшему судебному приставу, в подчинении которого\nнаходится судебный пристав-исполнитель или заместитель старшего судебного\nпристава. Жалоба на постановление должностного лица службы судебных\nприставов, его действия (бездействие) может быть подана как непосредственно\nвышестоящему должностному лицу службы судебных приставов, так и через\nдолжностное лицо службы судебных приставов, постановление, действия\n(бездействие) которого обжалуются. 2007 Nº\n229-Ф3 «Об исполнительном производстве», постановления судебного пристава-\nисполнителя и других должностных лиц службы судебных приставов, их действия\n(бездействие) по исполнению исполнительного документа могут быть обжалованы\nсторонами исполнительного производства, иными лицами, чьи права и интересы\nнарушены такими действиями, в порядке подчиненности и оспорены в суде. 2007 Nº 229-Ф3 «Об\nисполнительном производстве», жалоба на постановление судебного пристава-\nисполнителя или заместителя старшего судебного пристава, за исключением\nпостановления, утвержденного старшим судебным приставом, на их действия\n(бездействие) подается старшему судебному приставу, в подчинении которого\nнаходится судебный пристав-исполнитель или заместитель старшего судебного\nпристава. Жалоба на постановление должностного лица службы судебных\nприставов, его действия (бездействие) может быть подана как непосредственно\nвышестоящему должностному лицу службы судебных приставов, так и через\nдолжностное лицо службы судебных приставов, постановление, действия\n(бездействие) которого обжалуются. Разъясняем, что в соответствии с частью 4 статьи 5 Федерального закона\nNº 59-Ф3 от 02 мая 2006 года «О порядке рассмотрения обращений граждан РФ»,\nвы имеете право обращаться с жалобой на принятое по обращению решение в\nадминистративном или судебном порядке в соответствии с законодательством\nРФ. 2025\nNº\n1952*-2025/20450029/Он2713-25\nНа Nº\nБасманной межрайонной прокуратурой рассмотрено Ваше обращение\nпо вопросу нарушения процедуры постановки на учет транспортного средства,\nвх. Дополнительно сообщаем Вам необходимо обратиться в органы ДПС\nс целью снятия автомашины с учета которой Вы не пользуетесь с целью не\nплатить налог за автотранспорт которым пользуется другой гражданин. Так же сообщаем, что Ваше право обжаловать данное решение\nпрокурору или в суд в порядке, установленном статьей 124 или статьей 125\nуголовно процессуального кодекса Российской Федерации. Материал списать в номенклатурное делопроизводство. 2019 Nº733 \"Об общероссийских классификаторах технико-\nэкономической и социальной информации\"\nсудебный пристав-исполнитель Полтавчук А. Запрашиваемые данные:\nинформацию о наличии автомототранспорта (модель, госномер, под выпуска, цвет кузова, дата. 2021\n•Транспортные средства:\nЛегковые автомобили седан; Не указано; БМВ 730 D; 1999г. 000;\nПервичный ПТС (уникальный номер регистрации) 60ТА990056; Наименование технологической\nоперации Первичная регистрация ТС; Наименование регистрационного документа Свидетельство о\nрегистрации транспортного средства (приказ МВД России Nº 346-93); Серия и номер регистрационного\nдокумента 77MМ832193; Дата выдачи регистрационного документа 30. 2021\n• Транспортные средства:\nЛегковые автомобили прочие; Не указано; ВАЗ 21063; 1992г. 000; Наименование технологической операции\nПервичная регистрация ТС; Наименование регистрационного документа Технический паспорт; Дата\nвыдачи регистрационного документа 10. 2021\n•Транспортные средства:\nЛегковые автомобили прочие; Не указано; МАЗДА 929; 1987г. 000; Наименование технологической операции\nВыдача дубликата регистрационного документа; Наименование регистрационного документа\nТехнический паспорт; Серия и номер регистрационного документа ГЖ383874; Дата выдачи\nрегистрационного документа 12",
      "importance": 10
    },
    {
      "timestamp": "2025-10-22T00:40:02.086Z",
      "content": "2019 Nº733 \"Об обшероссийских классификаторах технико-\nэкономической и социальной информации\"\nсудебный пристав-исполинтель Полтавчук А. Запрашиваемые данные:\nинформацию о наличии автомототранспорта (молсль, госномер, под выпуска, ивст кузова. 2021\n• Транспортные средства:\nЛегковые автомобили седан; Не указано; БМВ 730 D; 1999г. документ: Свидетельство о регистрации транспортного средства (приказ МВД России Nº 346-93); Серия\nи номер: 77MM832193; Дата выдачи: 30. 2021\n• Транспортные средства:\nЛегковые автомобили прочис; Не указано; ВАЗ 21063; 1992г. документ: Технический паспорт; Дата\nвыдачи: 10. 2021\n• Транспортные средства:\nЛегковые автомобили прочие; Не указано; МАЗДА 929; 1987г. документ: Технический паспорт; Серия\nи номер: ГЖ383874; Дата выдачи: 12. 13:00 до 18:00\nот (полностью)_\nЕгорова\nЮрия Павловича\nСНИЛС:\nЦарицынский отдел судебчых приставо»\nBX. к 977 4937579\nгаспорт 45 07 Nº 08 2244\nзыдан ОРД. 20042\ne-mail ann 374 @yandex ru\nЗАЯВЛЕНИЕ\nПрошу приостаховить выполнение\nсудебного приказа в отконенни\nменя до окончання проверки\nмосго дела Нагатинской\nпрокурат урай. 124 Уголовно-\nпроцессуального кодекса Российской федерации, может быть обжаловано\nв Басманную межрайонную прокуратуру города Москвы или в суд. 2025\n23-33/049419@\nHa Nº\nО транспортном налоге (13734/3Г)\nЕгорову Ю. 2025 Nº330ж-2025/20450045/0н981-25, и сообщает, что по вопросу исчисления\nтранспортного налога на адрес Вашего места жительства, указанный в Вашем\nобращении, заказным письмом направлен ответ Управления от 20. Одновременно Управление сообщает, что согласно письму ГУ МВД России от\nNº45/17-288, транспортное средство, указанное в Вашем обращении, зарегистрировано\nна Ваше имя. Учитывая вышеизложенное, транспортный налог за указанное транспортное\nсредство по 2023 год включительно исчислен Вам ИФНС России Nº 24 по г. По вопросу снятия с регистрационного учета указанного транспортного средства\nВы вправе обратиться в органы ГИБДД. 2023 предусмотрена\nвозможность получения налоговых уведомлений для уплаты имущественных налогов\nв электронной форме через личный кабинет на едином портале государственных и\nмуниципальных услуг (ЕПГУ). 2007 Nº\n229-ФЗ «Об исполнительном производстве», постановления судебного пристава-\nисполнителя и других должностных лиц службы судебных приставов, их действия\n(бездействие) по исполнению исполнительного документа могут быть обжалованы\nсторонами исполнительного производства, иными лицами, чьи права и интересы\nнарушены такими действиями, в порядке подчиненности и оспорены в суде. 2007 Nº 229-Ф3 «Об\nисполнительном производстве», жалоба на постановление судебного пристава-\nисполнителя или заместителя старшего судебного пристава, за исключением\nпостановления, утвержденного старшим судебным приставом, на их действия\n(бездействие) подается старшему судебному приставу, в подчинении которого\nнаходится судебный пристав-исполнитель или заместитель старшего судебного\nпристава. Жалоба на постановление должностного лица службы судебных\nприставов, его действия (бездействие) может быть подана как непосредственно\nвышестоящему должностному лицу службы судебных приставов, так и через\nдолжностное лицо службы судебных приставов, постановление, действия\n(бездействие) которого обжалуются. 2007 Nº\n229-Ф3 «Об исполнительном производстве», постановления судебного пристава-\nисполнителя и других должностных лиц службы судебных приставов, их действия\n(бездействие) по исполнению исполнительного документа могут быть обжалованы\nсторонами исполнительного производства, иными лицами, чьи права и интересы\nнарушены такими действиями, в порядке подчиненности и оспорены в суде. 2007 Nº 229-Ф3 «Об\nисполнительном производстве», жалоба на постановление судебного пристава-\nисполнителя или заместителя старшего судебного пристава, за исключением\nпостановления, утвержденного старшим судебным приставом, на их действия\n(бездействие) подается старшему судебному приставу, в подчинении которого\nнаходится судебный пристав-исполнитель или заместитель старшего судебного\nпристава. Жалоба на постановление должностного лица службы судебных\nприставов, его действия (бездействие) может быть подана как непосредственно\nвышестоящему должностному лицу службы судебных приставов, так и через\nдолжностное лицо службы судебных приставов, постановление, действия\n(бездействие) которого обжалуются. Разъясняем, что в соответствии с частью 4 статьи 5 Федерального закона\nNº 59-Ф3 от 02 мая 2006 года «О порядке рассмотрения обращений граждан РФ»,\nвы имеете право обращаться с жалобой на принятое по обращению решение в\nадминистративном или судебном порядке в соответствии с законодательством\nРФ. 2025\nNº\n1952*-2025/20450029/Он2713-25\nНа Nº\nБасманной межрайонной прокуратурой рассмотрено Ваше обращение\nпо вопросу нарушения процедуры постановки на учет транспортного средства,\nвх. Дополнительно сообщаем Вам необходимо обратиться в органы ДПС\nс целью снятия автомашины с учета которой Вы не пользуетесь с целью не\nплатить налог за автотранспорт которым пользуется другой гражданин. Так же сообщаем, что Ваше право обжаловать данное решение\nпрокурору или в суд в порядке, установленном статьей 124 или статьей 125\nуголовно процессуального кодекса Российской Федерации. Материал списать в номенклатурное делопроизводство. 2019 Nº733 \"Об общероссийских классификаторах технико-\nэкономической и социальной информации\"\nсудебный пристав-исполнитель Полтавчук А. Запрашиваемые данные:\nинформацию о наличии автомототранспорта (модель, госномер, под выпуска, цвет кузова, дата. 2021\n•Транспортные средства:\nЛегковые автомобили седан; Не указано; БМВ 730 D; 1999г. 000;\nПервичный ПТС (уникальный номер регистрации) 60ТА990056; Наименование технологической\nоперации Первичная регистрация ТС; Наименование регистрационного документа Свидетельство о\nрегистрации транспортного средства (приказ МВД России Nº 346-93); Серия и номер регистрационного\nдокумента 77MМ832193; Дата выдачи регистрационного документа 30. 2021\n• Транспортные средства:\nЛегковые автомобили прочие; Не указано; ВАЗ 21063; 1992г. 000; Наименование технологической операции\nПервичная регистрация ТС; Наименование регистрационного документа Технический паспорт; Дата\nвыдачи регистрационного документа 10. 2021\n•Транспортные средства:\nЛегковые автомобили прочие; Не указано; МАЗДА 929; 1987г. 000; Наименование технологической операции\nВыдача дубликата регистрационного документа; Наименование регистрационного документа\nТехнический паспорт; Серия и номер регистрационного документа ГЖ383874; Дата выдачи\nрегистрационного документа 12",
      "importance": 10
    },
    {
      "timestamp": "2025-10-22T16:28:06.205Z",
      "content": "2019 Nº733 \"Об обшероссийских классификаторах технико-\nэкономической и социальной информации\"\nсудебный пристав-исполинтель Полтавчук А. Запрашиваемые данные:\nинформацию о наличии автомототранспорта (молсль, госномер, под выпуска, ивст кузова. 2021\n• Транспортные средства:\nЛегковые автомобили седан; Не указано; БМВ 730 D; 1999г. документ: Свидетельство о регистрации транспортного средства (приказ МВД России Nº 346-93); Серия\nи номер: 77MM832193; Дата выдачи: 30. 2021\n• Транспортные средства:\nЛегковые автомобили прочис; Не указано; ВАЗ 21063; 1992г. документ: Технический паспорт; Дата\nвыдачи: 10. 2021\n• Транспортные средства:\nЛегковые автомобили прочие; Не указано; МАЗДА 929; 1987г. документ: Технический паспорт; Серия\nи номер: ГЖ383874; Дата выдачи: 12. 13:00 до 18:00\nот (полностью)_\nЕгорова\nЮрия Павловича\nСНИЛС:\nЦарицынский отдел судебчых приставо»\nBX. к 977 4937579\nгаспорт 45 07 Nº 08 2244\nзыдан ОРД. 20042\ne-mail ann 374 @yandex ru\nЗАЯВЛЕНИЕ\nПрошу приостаховить выполнение\nсудебного приказа в отконенни\nменя до окончання проверки\nмосго дела Нагатинской\nпрокурат урай. 124 Уголовно-\nпроцессуального кодекса Российской федерации, может быть обжаловано\nв Басманную межрайонную прокуратуру города Москвы или в суд. 2025\n23-33/049419@\nHa Nº\nО транспортном налоге (13734/3Г)\nЕгорову Ю. 2025 Nº330ж-2025/20450045/0н981-25, и сообщает, что по вопросу исчисления\nтранспортного налога на адрес Вашего места жительства, указанный в Вашем\nобращении, заказным письмом направлен ответ Управления от 20. Одновременно Управление сообщает, что согласно письму ГУ МВД России от\nNº45/17-288, транспортное средство, указанное в Вашем обращении, зарегистрировано\nна Ваше имя. Учитывая вышеизложенное, транспортный налог за указанное транспортное\nсредство по 2023 год включительно исчислен Вам ИФНС России Nº 24 по г. По вопросу снятия с регистрационного учета указанного транспортного средства\nВы вправе обратиться в органы ГИБДД. 2023 предусмотрена\nвозможность получения налоговых уведомлений для уплаты имущественных налогов\nв электронной форме через личный кабинет на едином портале государственных и\nмуниципальных услуг (ЕПГУ). 2007 Nº\n229-ФЗ «Об исполнительном производстве», постановления судебного пристава-\nисполнителя и других должностных лиц службы судебных приставов, их действия\n(бездействие) по исполнению исполнительного документа могут быть обжалованы\nсторонами исполнительного производства, иными лицами, чьи права и интересы\nнарушены такими действиями, в порядке подчиненности и оспорены в суде. 2007 Nº 229-Ф3 «Об\nисполнительном производстве», жалоба на постановление судебного пристава-\nисполнителя или заместителя старшего судебного пристава, за исключением\nпостановления, утвержденного старшим судебным приставом, на их действия\n(бездействие) подается старшему судебному приставу, в подчинении которого\nнаходится судебный пристав-исполнитель или заместитель старшего судебного\nпристава. Жалоба на постановление должностного лица службы судебных\nприставов, его действия (бездействие) может быть подана как непосредственно\nвышестоящему должностному лицу службы судебных приставов, так и через\nдолжностное лицо службы судебных приставов, постановление, действия\n(бездействие) которого обжалуются. 2007 Nº\n229-Ф3 «Об исполнительном производстве», постановления судебного пристава-\nисполнителя и других должностных лиц службы судебных приставов, их действия\n(бездействие) по исполнению исполнительного документа могут быть обжалованы\nсторонами исполнительного производства, иными лицами, чьи права и интересы\nнарушены такими действиями, в порядке подчиненности и оспорены в суде. 2007 Nº 229-Ф3 «Об\nисполнительном производстве», жалоба на постановление судебного пристава-\nисполнителя или заместителя старшего судебного пристава, за исключением\nпостановления, утвержденного старшим судебным приставом, на их действия\n(бездействие) подается старшему судебному приставу, в подчинении которого\nнаходится судебный пристав-исполнитель или заместитель старшего судебного\nпристава. Жалоба на постановление должностного лица службы судебных\nприставов, его действия (бездействие) может быть подана как непосредственно\nвышестоящему должностному лицу службы судебных приставов, так и через\nдолжностное лицо службы судебных приставов, постановление, действия\n(бездействие) которого обжалуются. Разъясняем, что в соответствии с частью 4 статьи 5 Федерального закона\nNº 59-Ф3 от 02 мая 2006 года «О порядке рассмотрения обращений граждан РФ»,\nвы имеете право обращаться с жалобой на принятое по обращению решение в\nадминистративном или судебном порядке в соответствии с законодательством\nРФ. 2025\nNº\n1952*-2025/20450029/Он2713-25\nНа Nº\nБасманной межрайонной прокуратурой рассмотрено Ваше обращение\nпо вопросу нарушения процедуры постановки на учет транспортного средства,\nвх. Дополнительно сообщаем Вам необходимо обратиться в органы ДПС\nс целью снятия автомашины с учета которой Вы не пользуетесь с целью не\nплатить налог за автотранспорт которым пользуется другой гражданин. Так же сообщаем, что Ваше право обжаловать данное решение\nпрокурору или в суд в порядке, установленном статьей 124 или статьей 125\nуголовно процессуального кодекса Российской Федерации. Материал списать в номенклатурное делопроизводство. 2019 Nº733 \"Об общероссийских классификаторах технико-\nэкономической и социальной информации\"\nсудебный пристав-исполнитель Полтавчук А. Запрашиваемые данные:\nинформацию о наличии автомототранспорта (модель, госномер, под выпуска, цвет кузова, дата. 2021\n•Транспортные средства:\nЛегковые автомобили седан; Не указано; БМВ 730 D; 1999г. 000;\nПервичный ПТС (уникальный номер регистрации) 60ТА990056; Наименование технологической\nоперации Первичная регистрация ТС; Наименование регистрационного документа Свидетельство о\nрегистрации транспортного средства (приказ МВД России Nº 346-93); Серия и номер регистрационного\nдокумента 77MМ832193; Дата выдачи регистрационного документа 30. 2021\n• Транспортные средства:\nЛегковые автомобили прочие; Не указано; ВАЗ 21063; 1992г. 000; Наименование технологической операции\nПервичная регистрация ТС; Наименование регистрационного документа Технический паспорт; Дата\nвыдачи регистрационного документа 10. 2021\n•Транспортные средства:\nЛегковые автомобили прочие; Не указано; МАЗДА 929; 1987г. 000; Наименование технологической операции\nВыдача дубликата регистрационного документа; Наименование регистрационного документа\nТехнический паспорт; Серия и номер регистрационного документа ГЖ383874; Дата выдачи\nрегистрационного документа 12",
      "importance": 10
    },
    {
      "timestamp": "2025-10-22T16:40:30.018Z",
      "content": "2019 Nº733 \"Об обшероссийских классификаторах технико-\nэкономической и социальной информации\"\nсудебный пристав-исполинтель Полтавчук А. Запрашиваемые данные:\nинформацию о наличии автомототранспорта (молсль, госномер, под выпуска, ивст кузова. 2021\n• Транспортные средства:\nЛегковые автомобили седан; Не указано; БМВ 730 D; 1999г. документ: Свидетельство о регистрации транспортного средства (приказ МВД России Nº 346-93); Серия\nи номер: 77MM832193; Дата выдачи: 30. 2021\n• Транспортные средства:\nЛегковые автомобили прочис; Не указано; ВАЗ 21063; 1992г. документ: Технический паспорт; Дата\nвыдачи: 10. 2021\n• Транспортные средства:\nЛегковые автомобили прочие; Не указано; МАЗДА 929; 1987г. документ: Технический паспорт; Серия\nи номер: ГЖ383874; Дата выдачи: 12. 13:00 до 18:00\nот (полностью)_\nЕгорова\nЮрия Павловича\nСНИЛС:\nЦарицынский отдел судебчых приставо»\nBX. к 977 4937579\nгаспорт 45 07 Nº 08 2244\nзыдан ОРД. 20042\ne-mail ann 374 @yandex ru\nЗАЯВЛЕНИЕ\nПрошу приостаховить выполнение\nсудебного приказа в отконенни\nменя до окончання проверки\nмосго дела Нагатинской\nпрокурат урай. 124 Уголовно-\nпроцессуального кодекса Российской федерации, может быть обжаловано\nв Басманную межрайонную прокуратуру города Москвы или в суд. 2025\n23-33/049419@\nHa Nº\nО транспортном налоге (13734/3Г)\nЕгорову Ю. 2025 Nº330ж-2025/20450045/0н981-25, и сообщает, что по вопросу исчисления\nтранспортного налога на адрес Вашего места жительства, указанный в Вашем\nобращении, заказным письмом направлен ответ Управления от 20. Одновременно Управление сообщает, что согласно письму ГУ МВД России от\nNº45/17-288, транспортное средство, указанное в Вашем обращении, зарегистрировано\nна Ваше имя. Учитывая вышеизложенное, транспортный налог за указанное транспортное\nсредство по 2023 год включительно исчислен Вам ИФНС России Nº 24 по г. По вопросу снятия с регистрационного учета указанного транспортного средства\nВы вправе обратиться в органы ГИБДД. 2023 предусмотрена\nвозможность получения налоговых уведомлений для уплаты имущественных налогов\nв электронной форме через личный кабинет на едином портале государственных и\nмуниципальных услуг (ЕПГУ). 2007 Nº\n229-ФЗ «Об исполнительном производстве», постановления судебного пристава-\nисполнителя и других должностных лиц службы судебных приставов, их действия\n(бездействие) по исполнению исполнительного документа могут быть обжалованы\nсторонами исполнительного производства, иными лицами, чьи права и интересы\nнарушены такими действиями, в порядке подчиненности и оспорены в суде. 2007 Nº 229-Ф3 «Об\nисполнительном производстве», жалоба на постановление судебного пристава-\nисполнителя или заместителя старшего судебного пристава, за исключением\nпостановления, утвержденного старшим судебным приставом, на их действия\n(бездействие) подается старшему судебному приставу, в подчинении которого\nнаходится судебный пристав-исполнитель или заместитель старшего судебного\nпристава. Жалоба на постановление должностного лица службы судебных\nприставов, его действия (бездействие) может быть подана как непосредственно\nвышестоящему должностному лицу службы судебных приставов, так и через\nдолжностное лицо службы судебных приставов, постановление, действия\n(бездействие) которого обжалуются. 2007 Nº\n229-Ф3 «Об исполнительном производстве», постановления судебного пристава-\nисполнителя и других должностных лиц службы судебных приставов, их действия\n(бездействие) по исполнению исполнительного документа могут быть обжалованы\nсторонами исполнительного производства, иными лицами, чьи права и интересы\nнарушены такими действиями, в порядке подчиненности и оспорены в суде. 2007 Nº 229-Ф3 «Об\nисполнительном производстве», жалоба на постановление судебного пристава-\nисполнителя или заместителя старшего судебного пристава, за исключением\nпостановления, утвержденного старшим судебным приставом, на их действия\n(бездействие) подается старшему судебному приставу, в подчинении которого\nнаходится судебный пристав-исполнитель или заместитель старшего судебного\nпристава. Жалоба на постановление должностного лица службы судебных\nприставов, его действия (бездействие) может быть подана как непосредственно\nвышестоящему должностному лицу службы судебных приставов, так и через\nдолжностное лицо службы судебных приставов, постановление, действия\n(бездействие) которого обжалуются. Разъясняем, что в соответствии с частью 4 статьи 5 Федерального закона\nNº 59-Ф3 от 02 мая 2006 года «О порядке рассмотрения обращений граждан РФ»,\nвы имеете право обращаться с жалобой на принятое по обращению решение в\nадминистративном или судебном порядке в соответствии с законодательством\nРФ. 2025\nNº\n1952*-2025/20450029/Он2713-25\nНа Nº\nБасманной межрайонной прокуратурой рассмотрено Ваше обращение\nпо вопросу нарушения процедуры постановки на учет транспортного средства,\nвх. Дополнительно сообщаем Вам необходимо обратиться в органы ДПС\nс целью снятия автомашины с учета которой Вы не пользуетесь с целью не\nплатить налог за автотранспорт которым пользуется другой гражданин. Так же сообщаем, что Ваше право обжаловать данное решение\nпрокурору или в суд в порядке, установленном статьей 124 или статьей 125\nуголовно процессуального кодекса Российской Федерации. Материал списать в номенклатурное делопроизводство. 2019 Nº733 \"Об общероссийских классификаторах технико-\nэкономической и социальной информации\"\nсудебный пристав-исполнитель Полтавчук А. Запрашиваемые данные:\nинформацию о наличии автомототранспорта (модель, госномер, под выпуска, цвет кузова, дата. 2021\n•Транспортные средства:\nЛегковые автомобили седан; Не указано; БМВ 730 D; 1999г. 000;\nПервичный ПТС (уникальный номер регистрации) 60ТА990056; Наименование технологической\nоперации Первичная регистрация ТС; Наименование регистрационного документа Свидетельство о\nрегистрации транспортного средства (приказ МВД России Nº 346-93); Серия и номер регистрационного\nдокумента 77MМ832193; Дата выдачи регистрационного документа 30. 2021\n• Транспортные средства:\nЛегковые автомобили прочие; Не указано; ВАЗ 21063; 1992г. 000; Наименование технологической операции\nПервичная регистрация ТС; Наименование регистрационного документа Технический паспорт; Дата\nвыдачи регистрационного документа 10. 2021\n•Транспортные средства:\nЛегковые автомобили прочие; Не указано; МАЗДА 929; 1987г. 000; Наименование технологической операции\nВыдача дубликата регистрационного документа; Наименование регистрационного документа\nТехнический паспорт; Серия и номер регистрационного документа ГЖ383874; Дата выдачи\nрегистрационного документа 12",
      "importance": 10
    },
    {
      "timestamp": "2025-10-22T16:40:38.984Z",
      "content": "2019 Nº733 \"Об обшероссийских классификаторах технико-\nэкономической и социальной информации\"\nсудебный пристав-исполинтель Полтавчук А. Запрашиваемые данные:\nинформацию о наличии автомототранспорта (молсль, госномер, под выпуска, ивст кузова. 2021\n• Транспортные средства:\nЛегковые автомобили седан; Не указано; БМВ 730 D; 1999г. документ: Свидетельство о регистрации транспортного средства (приказ МВД России Nº 346-93); Серия\nи номер: 77MM832193; Дата выдачи: 30. 2021\n• Транспортные средства:\nЛегковые автомобили прочис; Не указано; ВАЗ 21063; 1992г. документ: Технический паспорт; Дата\nвыдачи: 10. 2021\n• Транспортные средства:\nЛегковые автомобили прочие; Не указано; МАЗДА 929; 1987г. документ: Технический паспорт; Серия\nи номер: ГЖ383874; Дата выдачи: 12. 13:00 до 18:00\nот (полностью)_\nЕгорова\nЮрия Павловича\nСНИЛС:\nЦарицынский отдел судебчых приставо»\nBX. к 977 4937579\nгаспорт 45 07 Nº 08 2244\nзыдан ОРД. 20042\ne-mail ann 374 @yandex ru\nЗАЯВЛЕНИЕ\nПрошу приостаховить выполнение\nсудебного приказа в отконенни\nменя до окончання проверки\nмосго дела Нагатинской\nпрокурат урай. 124 Уголовно-\nпроцессуального кодекса Российской федерации, может быть обжаловано\nв Басманную межрайонную прокуратуру города Москвы или в суд. 2025\n23-33/049419@\nHa Nº\nО транспортном налоге (13734/3Г)\nЕгорову Ю. 2025 Nº330ж-2025/20450045/0н981-25, и сообщает, что по вопросу исчисления\nтранспортного налога на адрес Вашего места жительства, указанный в Вашем\nобращении, заказным письмом направлен ответ Управления от 20. Одновременно Управление сообщает, что согласно письму ГУ МВД России от\nNº45/17-288, транспортное средство, указанное в Вашем обращении, зарегистрировано\nна Ваше имя. Учитывая вышеизложенное, транспортный налог за указанное транспортное\nсредство по 2023 год включительно исчислен Вам ИФНС России Nº 24 по г. По вопросу снятия с регистрационного учета указанного транспортного средства\nВы вправе обратиться в органы ГИБДД. 2023 предусмотрена\nвозможность получения налоговых уведомлений для уплаты имущественных налогов\nв электронной форме через личный кабинет на едином портале государственных и\nмуниципальных услуг (ЕПГУ). 2007 Nº\n229-ФЗ «Об исполнительном производстве», постановления судебного пристава-\nисполнителя и других должностных лиц службы судебных приставов, их действия\n(бездействие) по исполнению исполнительного документа могут быть обжалованы\nсторонами исполнительного производства, иными лицами, чьи права и интересы\nнарушены такими действиями, в порядке подчиненности и оспорены в суде. 2007 Nº 229-Ф3 «Об\nисполнительном производстве», жалоба на постановление судебного пристава-\nисполнителя или заместителя старшего судебного пристава, за исключением\nпостановления, утвержденного старшим судебным приставом, на их действия\n(бездействие) подается старшему судебному приставу, в подчинении которого\nнаходится судебный пристав-исполнитель или заместитель старшего судебного\nпристава. Жалоба на постановление должностного лица службы судебных\nприставов, его действия (бездействие) может быть подана как непосредственно\nвышестоящему должностному лицу службы судебных приставов, так и через\nдолжностное лицо службы судебных приставов, постановление, действия\n(бездействие) которого обжалуются. 2007 Nº\n229-Ф3 «Об исполнительном производстве», постановления судебного пристава-\nисполнителя и других должностных лиц службы судебных приставов, их действия\n(бездействие) по исполнению исполнительного документа могут быть обжалованы\nсторонами исполнительного производства, иными лицами, чьи права и интересы\nнарушены такими действиями, в порядке подчиненности и оспорены в суде. 2007 Nº 229-Ф3 «Об\nисполнительном производстве», жалоба на постановление судебного пристава-\nисполнителя или заместителя старшего судебного пристава, за исключением\nпостановления, утвержденного старшим судебным приставом, на их действия\n(бездействие) подается старшему судебному приставу, в подчинении которого\nнаходится судебный пристав-исполнитель или заместитель старшего судебного\nпристава. Жалоба на постановление должностного лица службы судебных\nприставов, его действия (бездействие) может быть подана как непосредственно\nвышестоящему должностному лицу службы судебных приставов, так и через\nдолжностное лицо службы судебных приставов, постановление, действия\n(бездействие) которого обжалуются. Разъясняем, что в соответствии с частью 4 статьи 5 Федерального закона\nNº 59-Ф3 от 02 мая 2006 года «О порядке рассмотрения обращений граждан РФ»,\nвы имеете право обращаться с жалобой на принятое по обращению решение в\nадминистративном или судебном порядке в соответствии с законодательством\nРФ. 2025\nNº\n1952*-2025/20450029/Он2713-25\nНа Nº\nБасманной межрайонной прокуратурой рассмотрено Ваше обращение\nпо вопросу нарушения процедуры постановки на учет транспортного средства,\nвх. Дополнительно сообщаем Вам необходимо обратиться в органы ДПС\nс целью снятия автомашины с учета которой Вы не пользуетесь с целью не\nплатить налог за автотранспорт которым пользуется другой гражданин. Так же сообщаем, что Ваше право обжаловать данное решение\nпрокурору или в суд в порядке, установленном статьей 124 или статьей 125\nуголовно процессуального кодекса Российской Федерации. Материал списать в номенклатурное делопроизводство. 2019 Nº733 \"Об общероссийских классификаторах технико-\nэкономической и социальной информации\"\nсудебный пристав-исполнитель Полтавчук А. Запрашиваемые данные:\nинформацию о наличии автомототранспорта (модель, госномер, под выпуска, цвет кузова, дата. 2021\n•Транспортные средства:\nЛегковые автомобили седан; Не указано; БМВ 730 D; 1999г. 000;\nПервичный ПТС (уникальный номер регистрации) 60ТА990056; Наименование технологической\nоперации Первичная регистрация ТС; Наименование регистрационного документа Свидетельство о\nрегистрации транспортного средства (приказ МВД России Nº 346-93); Серия и номер регистрационного\nдокумента 77MМ832193; Дата выдачи регистрационного документа 30. 2021\n• Транспортные средства:\nЛегковые автомобили прочие; Не указано; ВАЗ 21063; 1992г. 000; Наименование технологической операции\nПервичная регистрация ТС; Наименование регистрационного документа Технический паспорт; Дата\nвыдачи регистрационного документа 10. 2021\n•Транспортные средства:\nЛегковые автомобили прочие; Не указано; МАЗДА 929; 1987г. 000; Наименование технологической операции\nВыдача дубликата регистрационного документа; Наименование регистрационного документа\nТехнический паспорт; Серия и номер регистрационного документа ГЖ383874; Дата выдачи\nрегистрационного документа 12",
      "importance": 10
    },
    {
      "timestamp": "2025-10-22T16:58:04.570Z",
      "content": "2019 Nº733 \"Об обшероссийских классификаторах технико-\nэкономической и социальной информации\"\nсудебный пристав-исполинтель Полтавчук А. Запрашиваемые данные:\nинформацию о наличии автомототранспорта (молсль, госномер, под выпуска, ивст кузова. 2021\n• Транспортные средства:\nЛегковые автомобили седан; Не указано; БМВ 730 D; 1999г. документ: Свидетельство о регистрации транспортного средства (приказ МВД России Nº 346-93); Серия\nи номер: 77MM832193; Дата выдачи: 30. 2021\n• Транспортные средства:\nЛегковые автомобили прочис; Не указано; ВАЗ 21063; 1992г. документ: Технический паспорт; Дата\nвыдачи: 10. 2021\n• Транспортные средства:\nЛегковые автомобили прочие; Не указано; МАЗДА 929; 1987г. документ: Технический паспорт; Серия\nи номер: ГЖ383874; Дата выдачи: 12. 13:00 до 18:00\nот (полностью)_\nЕгорова\nЮрия Павловича\nСНИЛС:\nЦарицынский отдел судебчых приставо»\nBX. к 977 4937579\nгаспорт 45 07 Nº 08 2244\nзыдан ОРД. 20042\ne-mail ann 374 @yandex ru\nЗАЯВЛЕНИЕ\nПрошу приостаховить выполнение\nсудебного приказа в отконенни\nменя до окончання проверки\nмосго дела Нагатинской\nпрокурат урай. 124 Уголовно-\nпроцессуального кодекса Российской федерации, может быть обжаловано\nв Басманную межрайонную прокуратуру города Москвы или в суд. 2025\n23-33/049419@\nHa Nº\nО транспортном налоге (13734/3Г)\nЕгорову Ю. 2025 Nº330ж-2025/20450045/0н981-25, и сообщает, что по вопросу исчисления\nтранспортного налога на адрес Вашего места жительства, указанный в Вашем\nобращении, заказным письмом направлен ответ Управления от 20. Одновременно Управление сообщает, что согласно письму ГУ МВД России от\nNº45/17-288, транспортное средство, указанное в Вашем обращении, зарегистрировано\nна Ваше имя. Учитывая вышеизложенное, транспортный налог за указанное транспортное\nсредство по 2023 год включительно исчислен Вам ИФНС России Nº 24 по г. По вопросу снятия с регистрационного учета указанного транспортного средства\nВы вправе обратиться в органы ГИБДД. 2023 предусмотрена\nвозможность получения налоговых уведомлений для уплаты имущественных налогов\nв электронной форме через личный кабинет на едином портале государственных и\nмуниципальных услуг (ЕПГУ). 2007 Nº\n229-ФЗ «Об исполнительном производстве», постановления судебного пристава-\nисполнителя и других должностных лиц службы судебных приставов, их действия\n(бездействие) по исполнению исполнительного документа могут быть обжалованы\nсторонами исполнительного производства, иными лицами, чьи права и интересы\nнарушены такими действиями, в порядке подчиненности и оспорены в суде. 2007 Nº 229-Ф3 «Об\nисполнительном производстве», жалоба на постановление судебного пристава-\nисполнителя или заместителя старшего судебного пристава, за исключением\nпостановления, утвержденного старшим судебным приставом, на их действия\n(бездействие) подается старшему судебному приставу, в подчинении которого\nнаходится судебный пристав-исполнитель или заместитель старшего судебного\nпристава. Жалоба на постановление должностного лица службы судебных\nприставов, его действия (бездействие) может быть подана как непосредственно\nвышестоящему должностному лицу службы судебных приставов, так и через\nдолжностное лицо службы судебных приставов, постановление, действия\n(бездействие) которого обжалуются. 2007 Nº\n229-Ф3 «Об исполнительном производстве», постановления судебного пристава-\nисполнителя и других должностных лиц службы судебных приставов, их действия\n(бездействие) по исполнению исполнительного документа могут быть обжалованы\nсторонами исполнительного производства, иными лицами, чьи права и интересы\nнарушены такими действиями, в порядке подчиненности и оспорены в суде. 2007 Nº 229-Ф3 «Об\nисполнительном производстве», жалоба на постановление судебного пристава-\nисполнителя или заместителя старшего судебного пристава, за исключением\nпостановления, утвержденного старшим судебным приставом, на их действия\n(бездействие) подается старшему судебному приставу, в подчинении которого\nнаходится судебный пристав-исполнитель или заместитель старшего судебного\nпристава. Жалоба на постановление должностного лица службы судебных\nприставов, его действия (бездействие) может быть подана как непосредственно\nвышестоящему должностному лицу службы судебных приставов, так и через\nдолжностное лицо службы судебных приставов, постановление, действия\n(бездействие) которого обжалуются. Разъясняем, что в соответствии с частью 4 статьи 5 Федерального закона\nNº 59-Ф3 от 02 мая 2006 года «О порядке рассмотрения обращений граждан РФ»,\nвы имеете право обращаться с жалобой на принятое по обращению решение в\nадминистративном или судебном порядке в соответствии с законодательством\nРФ. 2025\nNº\n1952*-2025/20450029/Он2713-25\nНа Nº\nБасманной межрайонной прокуратурой рассмотрено Ваше обращение\nпо вопросу нарушения процедуры постановки на учет транспортного средства,\nвх. Дополнительно сообщаем Вам необходимо обратиться в органы ДПС\nс целью снятия автомашины с учета которой Вы не пользуетесь с целью не\nплатить налог за автотранспорт которым пользуется другой гражданин. Так же сообщаем, что Ваше право обжаловать данное решение\nпрокурору или в суд в порядке, установленном статьей 124 или статьей 125\nуголовно процессуального кодекса Российской Федерации. Материал списать в номенклатурное делопроизводство. 2019 Nº733 \"Об общероссийских классификаторах технико-\nэкономической и социальной информации\"\nсудебный пристав-исполнитель Полтавчук А. Запрашиваемые данные:\nинформацию о наличии автомототранспорта (модель, госномер, под выпуска, цвет кузова, дата. 2021\n•Транспортные средства:\nЛегковые автомобили седан; Не указано; БМВ 730 D; 1999г. 000;\nПервичный ПТС (уникальный номер регистрации) 60ТА990056; Наименование технологической\nоперации Первичная регистрация ТС; Наименование регистрационного документа Свидетельство о\nрегистрации транспортного средства (приказ МВД России Nº 346-93); Серия и номер регистрационного\nдокумента 77MМ832193; Дата выдачи регистрационного документа 30. 2021\n• Транспортные средства:\nЛегковые автомобили прочие; Не указано; ВАЗ 21063; 1992г. 000; Наименование технологической операции\nПервичная регистрация ТС; Наименование регистрационного документа Технический паспорт; Дата\nвыдачи регистрационного документа 10. 2021\n•Транспортные средства:\nЛегковые автомобили прочие; Не указано; МАЗДА 929; 1987г. 000; Наименование технологической операции\nВыдача дубликата регистрационного документа; Наименование регистрационного документа\nТехнический паспорт; Серия и номер регистрационного документа ГЖ383874; Дата выдачи\nрегистрационного документа 12",
      "importance": 10
    },
    {
      "timestamp": "2025-10-22T17:00:18.404Z",
      "content": "2019 Nº733 \"Об обшероссийских классификаторах технико-\nэкономической и социальной информации\"\nсудебный пристав-исполинтель Полтавчук А. Запрашиваемые данные:\nинформацию о наличии автомототранспорта (молсль, госномер, под выпуска, ивст кузова. 2021\n• Транспортные средства:\nЛегковые автомобили седан; Не указано; БМВ 730 D; 1999г. документ: Свидетельство о регистрации транспортного средства (приказ МВД России Nº 346-93); Серия\nи номер: 77MM832193; Дата выдачи: 30. 2021\n• Транспортные средства:\nЛегковые автомобили прочис; Не указано; ВАЗ 21063; 1992г. документ: Технический паспорт; Дата\nвыдачи: 10. 2021\n• Транспортные средства:\nЛегковые автомобили прочие; Не указано; МАЗДА 929; 1987г. документ: Технический паспорт; Серия\nи номер: ГЖ383874; Дата выдачи: 12. 13:00 до 18:00\nот (полностью)_\nЕгорова\nЮрия Павловича\nСНИЛС:\nЦарицынский отдел судебчых приставо»\nBX. к 977 4937579\nгаспорт 45 07 Nº 08 2244\nзыдан ОРД. 20042\ne-mail ann 374 @yandex ru\nЗАЯВЛЕНИЕ\nПрошу приостаховить выполнение\nсудебного приказа в отконенни\nменя до окончання проверки\nмосго дела Нагатинской\nпрокурат урай. 124 Уголовно-\nпроцессуального кодекса Российской федерации, может быть обжаловано\nв Басманную межрайонную прокуратуру города Москвы или в суд. 2025\n23-33/049419@\nHa Nº\nО транспортном налоге (13734/3Г)\nЕгорову Ю. 2025 Nº330ж-2025/20450045/0н981-25, и сообщает, что по вопросу исчисления\nтранспортного налога на адрес Вашего места жительства, указанный в Вашем\nобращении, заказным письмом направлен ответ Управления от 20. Одновременно Управление сообщает, что согласно письму ГУ МВД России от\nNº45/17-288, транспортное средство, указанное в Вашем обращении, зарегистрировано\nна Ваше имя. Учитывая вышеизложенное, транспортный налог за указанное транспортное\nсредство по 2023 год включительно исчислен Вам ИФНС России Nº 24 по г. По вопросу снятия с регистрационного учета указанного транспортного средства\nВы вправе обратиться в органы ГИБДД. 2023 предусмотрена\nвозможность получения налоговых уведомлений для уплаты имущественных налогов\nв электронной форме через личный кабинет на едином портале государственных и\nмуниципальных услуг (ЕПГУ). 2007 Nº\n229-ФЗ «Об исполнительном производстве», постановления судебного пристава-\nисполнителя и других должностных лиц службы судебных приставов, их действия\n(бездействие) по исполнению исполнительного документа могут быть обжалованы\nсторонами исполнительного производства, иными лицами, чьи права и интересы\nнарушены такими действиями, в порядке подчиненности и оспорены в суде. 2007 Nº 229-Ф3 «Об\nисполнительном производстве», жалоба на постановление судебного пристава-\nисполнителя или заместителя старшего судебного пристава, за исключением\nпостановления, утвержденного старшим судебным приставом, на их действия\n(бездействие) подается старшему судебному приставу, в подчинении которого\nнаходится судебный пристав-исполнитель или заместитель старшего судебного\nпристава. Жалоба на постановление должностного лица службы судебных\nприставов, его действия (бездействие) может быть подана как непосредственно\nвышестоящему должностному лицу службы судебных приставов, так и через\nдолжностное лицо службы судебных приставов, постановление, действия\n(бездействие) которого обжалуются. 2007 Nº\n229-Ф3 «Об исполнительном производстве», постановления судебного пристава-\nисполнителя и других должностных лиц службы судебных приставов, их действия\n(бездействие) по исполнению исполнительного документа могут быть обжалованы\nсторонами исполнительного производства, иными лицами, чьи права и интересы\nнарушены такими действиями, в порядке подчиненности и оспорены в суде. 2007 Nº 229-Ф3 «Об\nисполнительном производстве», жалоба на постановление судебного пристава-\nисполнителя или заместителя старшего судебного пристава, за исключением\nпостановления, утвержденного старшим судебным приставом, на их действия\n(бездействие) подается старшему судебному приставу, в подчинении которого\nнаходится судебный пристав-исполнитель или заместитель старшего судебного\nпристава. Жалоба на постановление должностного лица службы судебных\nприставов, его действия (бездействие) может быть подана как непосредственно\nвышестоящему должностному лицу службы судебных приставов, так и через\nдолжностное лицо службы судебных приставов, постановление, действия\n(бездействие) которого обжалуются. Разъясняем, что в соответствии с частью 4 статьи 5 Федерального закона\nNº 59-Ф3 от 02 мая 2006 года «О порядке рассмотрения обращений граждан РФ»,\nвы имеете право обращаться с жалобой на принятое по обращению решение в\nадминистративном или судебном порядке в соответствии с законодательством\nРФ. 2025\nNº\n1952*-2025/20450029/Он2713-25\nНа Nº\nБасманной межрайонной прокуратурой рассмотрено Ваше обращение\nпо вопросу нарушения процедуры постановки на учет транспортного средства,\nвх. Дополнительно сообщаем Вам необходимо обратиться в органы ДПС\nс целью снятия автомашины с учета которой Вы не пользуетесь с целью не\nплатить налог за автотранспорт которым пользуется другой гражданин. Так же сообщаем, что Ваше право обжаловать данное решение\nпрокурору или в суд в порядке, установленном статьей 124 или статьей 125\nуголовно процессуального кодекса Российской Федерации. Материал списать в номенклатурное делопроизводство. 2019 Nº733 \"Об общероссийских классификаторах технико-\nэкономической и социальной информации\"\nсудебный пристав-исполнитель Полтавчук А. Запрашиваемые данные:\nинформацию о наличии автомототранспорта (модель, госномер, под выпуска, цвет кузова, дата. 2021\n•Транспортные средства:\nЛегковые автомобили седан; Не указано; БМВ 730 D; 1999г. 000;\nПервичный ПТС (уникальный номер регистрации) 60ТА990056; Наименование технологической\nоперации Первичная регистрация ТС; Наименование регистрационного документа Свидетельство о\nрегистрации транспортного средства (приказ МВД России Nº 346-93); Серия и номер регистрационного\nдокумента 77MМ832193; Дата выдачи регистрационного документа 30. 2021\n• Транспортные средства:\nЛегковые автомобили прочие; Не указано; ВАЗ 21063; 1992г. 000; Наименование технологической операции\nПервичная регистрация ТС; Наименование регистрационного документа Технический паспорт; Дата\nвыдачи регистрационного документа 10. 2021\n•Транспортные средства:\nЛегковые автомобили прочие; Не указано; МАЗДА 929; 1987г. 000; Наименование технологической операции\nВыдача дубликата регистрационного документа; Наименование регистрационного документа\nТехнический паспорт; Серия и номер регистрационного документа ГЖ383874; Дата выдачи\nрегистрационного документа 12",
      "importance": 10
    },
    {
      "timestamp": "2025-10-28T01:18:36.441Z",
      "content": "Я ничего не подписывал, и узнал что на мне кредит только когда на почту пришла повестка в суд",
      "importance": 3
    },
    {
      "timestamp": "2025-10-28T01:54:04.484Z",
      "content": "Я ничего не подписывал, и узнал что на мне кредит только когда на почту пришла повестка в суд",
      "importance": 3
    },
    {
      "timestamp": "2025-10-28T02:12:19.092Z",
      "content": "Я ничего не подписывал, и узнал что на мне кредит только когда на почту пришла повестка в суд",
      "importance": 3
    },
    {
      "timestamp": "2025-10-28T02:14:13.249Z",
      "content": "правоохранительные органы о факте мошенничества - в МВД и прокуратуре отказались начинать уголовное дело",
      "importance": 3
    },
    {
      "timestamp": "2025-10-28T02:32:21.364Z",
      "content": "Я ничего не подписывал, и узнал что на мне кредит только когда на почту пришла повестка в суд",
      "importance": 3
    },
    {
      "timestamp": "2025-10-28T02:37:19.847Z",
      "content": "Я ничего не подписывал, и узнал что на мне кредит только когда на почту пришла повестка в суд",
      "importance": 3
    },
    {
      "timestamp": "2025-10-28T02:55:27.613Z",
      "content": "а можно мне текст в суд что бы я в суде говорил твой текст",
      "importance": 3
    },
    {
      "timestamp": "2025-10-28T02:57:25.682Z",
      "content": "подготовь мне речь для суда",
      "importance": 3
    },
    {
      "timestamp": "2025-10-28T03:10:49.805Z",
      "content": "Я ничего не подписывал, и узнал что на мне кредит только когда на почту пришла повестка в суд",
      "importance": 3
    },
    {
      "timestamp": "2025-10-28T03:12:17.982Z",
      "content": "как мне защищаться на суде",
      "importance": 3
    },
    {
      "timestamp": "2025-10-28T03:51:11.964Z",
      "content": "Я ничего не подписывал, и узнал что на мне кредит только когда на почту пришла повестка в суд",
      "importance": 3
    },
    {
      "timestamp": "2025-10-28T04:07:30.010Z",
      "content": "Я ничего не подписывал, и узнал что на мне кредит только когда на почту пришла повестка в суд",
      "importance": 3
    },
    {
      "timestamp": "2025-10-28T04:19:52.683Z",
      "content": "Я ничего не подписывал, и узнал что на мне кредит только когда на почту пришла повестка в суд",
      "importance": 3
    },
    {
      "timestamp": "2025-10-28T05:14:55.726Z",
      "content": "Я ничего не подписывал, и узнал что на мне кредит только когда на почту пришла повестка в суд",
      "importance": 3
    },
    {
      "timestamp": "2025-10-28T05:17:22.213Z",
      "content": "Я ничего не подписывал, и узнал что на мне кредит только когда на почту пришла повестка в суд",
      "importance": 3
    },
    {
      "timestamp": "2025-10-28T05:19:05.018Z",
      "content": "что мне говорить в суде",
      "importance": 3
    },
    {
      "timestamp": "2025-10-28T05:20:17.920Z",
      "content": "что мне говорить в суде",
      "importance": 3
    },
    {
      "timestamp": "2025-10-28T05:23:21.488Z",
      "content": "Я ничего не подписывал, а теперь пришла повестка в суд",
      "importance": 4
    },
    {
      "timestamp": "2025-10-28T05:24:48.448Z",
      "content": "Я ничего не подписывал, а теперь пришла повестка в суд",
      "importance": 4
    },
    {
      "timestamp": "2025-10-28T05:27:34.192Z",
      "content": "Я ничего не подписывал, и узнал что на мне кредит только когда на почту пришла повестка в суд",
      "importance": 3
    },
    {
      "timestamp": "2025-10-28T05:29:25.656Z",
      "content": "Я ничего не подписывал, и узнал что на мне кредит только когда на почту пришла повестка в суд",
      "importance": 3
    },
    {
      "timestamp": "2025-10-28T06:28:24.170Z",
      "content": "Я ничего не подписывал, и узнал что на мне кредит только когда на почту пришла повестка в суд",
      "importance": 3
    },
    {
      "timestamp": "2025-10-28T06:51:11.854Z",
      "content": "Я ничего не подписывал, и узнал что на мне кредит только когда на почту пришла повестка в суд",
      "importance": 3
    },
    {
      "timestamp": "2025-10-28T07:15:51.444Z",
      "content": "Я ничего не подписывал, и узнал что на мне кредит только когда на почту пришла повестка в суд",
      "importance": 3
    },
    {
      "timestamp": "2025-10-28T07:19:23.384Z",
      "content": "Я ничего не подписывал, и узнал что на мне кредит только когда на почту пришла повестка в суд",
      "importance": 3
    },
    {
      "timestamp": "2025-10-28T09:07:08.169Z",
      "content": "docx\n\nРаспознанный текст:\nДоговор субподряда на выполнение работ №271025/19\n\nГ. 2025\n\nИндивидуальный предприниматель Сергутин Ярослав Игоревич в лице Сергутина Ярослава Игоревича, действующего на основании Листа записи Единого государственного реестра индивидуальных предпринимателей, выданного 16. 2024г, ГРН 324570000019103, именуемый в дальнейшем \"Генеральный подрядчик\", с одной стороны и\n\nИндивидуальный предприниматель Бутко Артем Михайлович в лице Бутко Артема Михайловича, действующего на основании Листа записи Единого государственного реестра индивидуальных предпринимателей, выданного 26. 2025г, ГРН 325237500077534, именуемый в дальнейшем \"Субподрядчик\", с другой стороны, а вместе именуемые \"Стороны\", заключили договор о нижеследующем:\n\n1. Предмет договора\n\n1. По настоящему договору Генеральный подрядчик с согласия Заказчика привлекает к исполнению своих обязательств по договору подряда оказания услуг от 27. В рамках настоящего договора Субподрядчик по поручению Генерального подрядчика принимает на себя выполнение комплекса работ: разработка и передача Заказчику трекеры TrackAI (далее – оборудование) в количестве 10 (десяти) штук, консультации персонала Заказчика по работе с оборудованием, предоставление Заказчику подписки на ПО TrackService и облачные вычисления, а Генеральный подрядчик обязуется принять результат работы и оплатить его. Субподрядчик обязуется выполнять предусмотренные настоящим договором работы в соответствии с технической документацией, определяющей объем, содержание работ и другие предъявляемые к ним требования, и со сметой, определяющей цену работ, а Подрядчик обязуется создать Субподрядчику необходимые условия для выполнения работ, принять их результат и уплатить обусловленную цену в сроки, в порядке и на условиях, установленных в настоящем договоре. Перечень технической документации (Приложение 1) является неотъемлемой частью настоящего договора. Субподрядчик должен приступить к выполнению работы по договору не позднее 28. Указанные в договоре сроки выполнения работ могут быть изменены по соглашению Сторон. Все оборудование Субподрядчика имеет надлежащие сертификаты, лицензии, паспорта, инструкции по эксплуатации, соответствующие требованиям законодательства РФ. Права и обязанности сторон договора\n\n2. Обеспечить наличие на все используемые при выполнении работ материалы, изделия, ПО соответствующих сертификатов, технических паспортов и других документов, удостоверяющих их качество. Исполнять полученные в ходе работ указания Генерального подрядчика, если такие указания не противоречат условиям настоящего договора и не представляют собой вмешательство в оперативно-хозяйственную деятельность Субподрядчика. Самостоятельно определять способы выполнения работы по настоящему договору. Немедленно заявить Субподрядчику об обнаружении при осуществлении контроля и надзора за выполнением работ отступлений от условий настоящего договора, которые могут ухудшить качество работ, или иных их недостатков. Предоставлять Субподрядчику все документы и информацию, необходимые для выполнения Субподрядчиком своих обязательств по настоящему договору. Уплатить Субподрядчику обусловленную цену в порядке и сроки, установленные настоящим договором. Привлекать независимых экспертов для проверки соответствия качества выполняемых работ требованиям, установленным настоящим договором. Назначить Субподрядчику разумный срок для устранения недостатков в случае выявления ненадлежащего выполнения работы и при неисполнении Субподрядчиком в назначенный срок этого требования отказаться от настоящего договора либо поручить исправление работ другому лицу за счет Субподрядчика, а также потребовать возмещения убытков. Цена выполняемой работы по настоящему договору определена путем составления сметы и составляет 195000 (сто девяносто пять тысяч) рублей, без НДС, которая включает в себя компенсацию издержек Субподрядчика и причитающееся ему вознаграждение. Смета составляется Субподрядчиком, приобретает силу и становится частью настоящего договора с момента утверждения ее Генеральным подрядчиком. По настоящему договору цена работы считается твердой. В случае неисполнения или ненадлежащего исполнения своих обязательств по настоящему договору Стороны несут ответственность в соответствии с действующим законодательством Российской Федерации. За нарушение срока выполнения работы, установленного настоящим договором, Субподрядчик уплачивает Генеральному подрядчику штраф в размере 40 (сорок) процентов от стоимости выполняемой работы. За нарушение сроков оплаты выполненной работы Генеральный подрядчик уплачивает Субподрядчику неустойку в размере 2 (двух) процентов от суммы долга за каждый день просрочки. Сторона освобождается от уплаты неустойки (штрафа, пени), если докажет, что неисполнение или ненадлежащее исполнение обязательства, предусмотренного договором, произошло вследствие непреодолимой силы или по вине другой Стороны. Результат выполненной работы должен в момент передачи Генеральному подрядчику обладать свойствами, указанными в настоящем договоре или определенными обычно предъявляемыми требованиями, и в пределах разумного срока быть пригодным для установленного настоящим договором использования либо для обычного использования результата работы такого рода. Порядок разрешения споров\n\n6. Споры и разногласия, которые могут возникнуть при исполнении настоящего договора, будут по возможности разрешаться путем переговоров между Сторонами. В случае если Стороны не придут к соглашению, споры разрешаются в судебном порядке в соответствии с действующим законодательством Российской Федерации. Настоящий договор составлен в двух экземплярах, имеющих одинаковую юридическую силу, по одному экземпляру для каждой из Сторон. Договор вступает в силу с момента подписания и действует до полного выполнения обязательств по настоящему договору. Все изменения и дополнения к настоящему договору оформляются дополнительными соглашениями Сторон в письменной форме, которые являются неотъемлемой частью настоящего договора. Заявления, уведомления, извещения, требования или иные юридически значимые сообщения, с которыми договор связывает гражданско-правовые последствия для Сторон настоящего договора, влекут для этого лица такие последствия с момента доставки соответствующего сообщения Стороне или ее представителю. Во всем остальном, что не предусмотрено настоящим договором, Стороны руководствуются законодательством Российской Федерации. Бутко\n\n\n\n\n\n\n\n\n\n\n\n\n\n\n\n\n\n\n\n\n\n\n\n\n\n\n\n\n\n\n\n\n\n\n\n\n\n\n\n\n\n\n\n\n\n\n\nПриложение № 1 к Договору на оказание услуг №271025/19 от 27 октября 2025 г. (сорок восемь тысяч семьсот пятьдесят рублей), в течение 3 (трех) рабочих дней с момента подписания Договора, после чего Исполнитель приступает к оказанию услуг. Исполнитель обязуется осуществлять консультации Заказчика по правильной технологии срока действия Договора",
      "importance": 10
    },
    {
      "timestamp": "2025-10-28T09:45:51.401Z",
      "content": "docx\n\nРаспознанный текст:\nДоговор субподряда на выполнение работ №271025/19\n\nГ. 2025\n\nИндивидуальный предприниматель Сергутин Ярослав Игоревич в лице Сергутина Ярослава Игоревича, действующего на основании Листа записи Единого государственного реестра индивидуальных предпринимателей, выданного 16. 2024г, ГРН 324570000019103, именуемый в дальнейшем \"Генеральный подрядчик\", с одной стороны и\n\nИндивидуальный предприниматель Бутко Артем Михайлович в лице Бутко Артема Михайловича, действующего на основании Листа записи Единого государственного реестра индивидуальных предпринимателей, выданного 26. 2025г, ГРН 325237500077534, именуемый в дальнейшем \"Субподрядчик\", с другой стороны, а вместе именуемые \"Стороны\", заключили договор о нижеследующем:\n\n1. Предмет договора\n\n1. По настоящему договору Генеральный подрядчик с согласия Заказчика привлекает к исполнению своих обязательств по договору подряда оказания услуг от 27. В рамках настоящего договора Субподрядчик по поручению Генерального подрядчика принимает на себя выполнение комплекса работ: разработка и передача Заказчику трекеры TrackAI (далее – оборудование) в количестве 10 (десяти) штук, консультации персонала Заказчика по работе с оборудованием, предоставление Заказчику подписки на ПО TrackService и облачные вычисления, а Генеральный подрядчик обязуется принять результат работы и оплатить его. Субподрядчик обязуется выполнять предусмотренные настоящим договором работы в соответствии с технической документацией, определяющей объем, содержание работ и другие предъявляемые к ним требования, и со сметой, определяющей цену работ, а Подрядчик обязуется создать Субподрядчику необходимые условия для выполнения работ, принять их результат и уплатить обусловленную цену в сроки, в порядке и на условиях, установленных в настоящем договоре. Перечень технической документации (Приложение 1) является неотъемлемой частью настоящего договора. Субподрядчик должен приступить к выполнению работы по договору не позднее 28. Указанные в договоре сроки выполнения работ могут быть изменены по соглашению Сторон. Все оборудование Субподрядчика имеет надлежащие сертификаты, лицензии, паспорта, инструкции по эксплуатации, соответствующие требованиям законодательства РФ. Права и обязанности сторон договора\n\n2. Обеспечить наличие на все используемые при выполнении работ материалы, изделия, ПО соответствующих сертификатов, технических паспортов и других документов, удостоверяющих их качество. Исполнять полученные в ходе работ указания Генерального подрядчика, если такие указания не противоречат условиям настоящего договора и не представляют собой вмешательство в оперативно-хозяйственную деятельность Субподрядчика. Самостоятельно определять способы выполнения работы по настоящему договору. Немедленно заявить Субподрядчику об обнаружении при осуществлении контроля и надзора за выполнением работ отступлений от условий настоящего договора, которые могут ухудшить качество работ, или иных их недостатков. Предоставлять Субподрядчику все документы и информацию, необходимые для выполнения Субподрядчиком своих обязательств по настоящему договору. Уплатить Субподрядчику обусловленную цену в порядке и сроки, установленные настоящим договором. Привлекать независимых экспертов для проверки соответствия качества выполняемых работ требованиям, установленным настоящим договором. Назначить Субподрядчику разумный срок для устранения недостатков в случае выявления ненадлежащего выполнения работы и при неисполнении Субподрядчиком в назначенный срок этого требования отказаться от настоящего договора либо поручить исправление работ другому лицу за счет Субподрядчика, а также потребовать возмещения убытков. Цена выполняемой работы по настоящему договору определена путем составления сметы и составляет 195000 (сто девяносто пять тысяч) рублей, без НДС, которая включает в себя компенсацию издержек Субподрядчика и причитающееся ему вознаграждение. Смета составляется Субподрядчиком, приобретает силу и становится частью настоящего договора с момента утверждения ее Генеральным подрядчиком. По настоящему договору цена работы считается твердой. В случае неисполнения или ненадлежащего исполнения своих обязательств по настоящему договору Стороны несут ответственность в соответствии с действующим законодательством Российской Федерации. За нарушение срока выполнения работы, установленного настоящим договором, Субподрядчик уплачивает Генеральному подрядчику штраф в размере 40 (сорок) процентов от стоимости выполняемой работы. За нарушение сроков оплаты выполненной работы Генеральный подрядчик уплачивает Субподрядчику неустойку в размере 2 (двух) процентов от суммы долга за каждый день просрочки. Сторона освобождается от уплаты неустойки (штрафа, пени), если докажет, что неисполнение или ненадлежащее исполнение обязательства, предусмотренного договором, произошло вследствие непреодолимой силы или по вине другой Стороны. Результат выполненной работы должен в момент передачи Генеральному подрядчику обладать свойствами, указанными в настоящем договоре или определенными обычно предъявляемыми требованиями, и в пределах разумного срока быть пригодным для установленного настоящим договором использования либо для обычного использования результата работы такого рода. Порядок разрешения споров\n\n6. Споры и разногласия, которые могут возникнуть при исполнении настоящего договора, будут по возможности разрешаться путем переговоров между Сторонами. В случае если Стороны не придут к соглашению, споры разрешаются в судебном порядке в соответствии с действующим законодательством Российской Федерации. Настоящий договор составлен в двух экземплярах, имеющих одинаковую юридическую силу, по одному экземпляру для каждой из Сторон. Договор вступает в силу с момента подписания и действует до полного выполнения обязательств по настоящему договору. Все изменения и дополнения к настоящему договору оформляются дополнительными соглашениями Сторон в письменной форме, которые являются неотъемлемой частью настоящего договора. Заявления, уведомления, извещения, требования или иные юридически значимые сообщения, с которыми договор связывает гражданско-правовые последствия для Сторон настоящего договора, влекут для этого лица такие последствия с момента доставки соответствующего сообщения Стороне или ее представителю. Во всем остальном, что не предусмотрено настоящим договором, Стороны руководствуются законодательством Российской Федерации. Бутко\n\n\n\n\n\n\n\n\n\n\n\n\n\n\n\n\n\n\n\n\n\n\n\n\n\n\n\n\n\n\n\n\n\n\n\n\n\n\n\n\n\n\n\n\n\n\n\nПриложение № 1 к Договору на оказание услуг №271025/19 от 27 октября 2025 г. (сорок восемь тысяч семьсот пятьдесят рублей), в течение 3 (трех) рабочих дней с момента подписания Договора, после чего Исполнитель приступает к оказанию услуг. Исполнитель обязуется осуществлять консультации Заказчика по правильной технологии срока действия Договора",
      "importance": 10
    },
    {
      "timestamp": "2025-10-28T10:00:37.673Z",
      "content": "подготовь мне речь для суда, что бы я мог платить меньше штрафа, хотя бы не 40% а 20%",
      "importance": 3
    }
  ],
  "preferences": {
    "autoSavePersonalData": true,
    "dataRetentionDays": 365,
    "privacyLevel": "standard"
  },
  "statistics": {
    "totalMessages": 0,
    "dataExtractionCount": 43,
    "lastActivity": "2025-10-28T10:00:37.676Z"
  }
}